depster/__init__.py
depster/depster.py
depster-1.1.1.dist-info/LICENSE
depster-1.1.1.dist-info/METADATA
depster-1.1.1.dist-info/WHEEL
depster-1.1.1.dist-info/entry_points.txt
depster-1.1.1.dist-info/top_level.txt
depster-1.1.1.dist-info/RECORD
