Metadata-Version: 2.1
Name: depster
Version: 1.1.1
Summary: A tool create a detailed CSV analyzing your project's dependencies
Home-page: https://github.com/shbenzer/depster
Author: Simon H. Benzer
Author-email: SimonHBenzer@gmail.com
Classifier: Programming Language :: Python :: 3
Classifier: License :: OSI Approved :: MIT License
Classifier: Operating System :: OS Independent
Requires-Python: >=3.6
License-File: LICENSE
Requires-Dist: pandas
Requires-Dist: requests
